tsml_eval/__init__.py
tsml_eval/_wip/__init__.py
tsml_eval/_wip/catch22/__init__.py
tsml_eval/_wip/catch22/_catch22.py
tsml_eval/_wip/catch22/_test_catch22.py
tsml_eval/_wip/catch22/aeon_catch22_no_numba.csv
tsml_eval/_wip/catch22/aeon_catch22_no_numba.xlsx
tsml_eval/_wip/catch22/aeon_catch22_with_numba.csv
tsml_eval/_wip/catch22/aeon_catch22_with_numba.xlsx
tsml_eval/_wip/catch22/pycatch22_catch22_ipd.csv
tsml_eval/_wip/catch22/pycatch22_catch22_ipd.xlsx
tsml_eval/_wip/dilation_muse/__init__.py
tsml_eval/_wip/dilation_muse/muse.py
tsml_eval/_wip/dilation_muse/sfa_dilation.py
tsml_eval/_wip/experiments/__init__.py
tsml_eval/_wip/experiments/collate_results.py
tsml_eval/_wip/experiments/results_summary.py
tsml_eval/_wip/forecasting/__init__.py
tsml_eval/_wip/forecasting/base.py
tsml_eval/_wip/forecasting/es_comparison2.py
tsml_eval/_wip/forecasting/ets.py
tsml_eval/_wip/forecasting/example_uses.py
tsml_eval/_wip/forecasting/exponential_smoothing.py
tsml_eval/_wip/forecasting/exponential_smoothing_comparison.py
tsml_eval/_wip/forecasting/nixtla.py
tsml_eval/_wip/forecasting/window_base.py
tsml_eval/_wip/forecasting/tests/__init__.py
tsml_eval/_wip/forecasting/tests/test_ets.py
tsml_eval/_wip/forecasting/tests/test_window_based.py
tsml_eval/_wip/hc2_regression/__init__.py
tsml_eval/_wip/hc2_regression/arsenal.py
tsml_eval/_wip/hc2_regression/hivecote_v2.py
tsml_eval/_wip/hc2_regression/sfa.py
tsml_eval/_wip/hc2_regression/shapelet_transform.py
tsml_eval/_wip/hc2_regression/str.py
tsml_eval/_wip/hc2_regression/tde.py
tsml_eval/_wip/pf/__init__.py
tsml_eval/_wip/pf/_pf2.py
tsml_eval/_wip/rt/__init__.py
tsml_eval/_wip/rt/classification/__init__.py
tsml_eval/_wip/rt/classification/distance_based/__init__.py
tsml_eval/_wip/rt/classification/distance_based/_time_series_neighbors.py
tsml_eval/_wip/rt/clustering/__init__.py
tsml_eval/_wip/rt/clustering/averaging/__init__.py
tsml_eval/_wip/rt/clustering/averaging/_ba_utils.py
tsml_eval/_wip/rt/distances/__init__.py
tsml_eval-0.6.0.dist-info/licenses/LICENSE
tsml_eval-0.6.0.dist-info/METADATA
tsml_eval-0.6.0.dist-info/WHEEL
tsml_eval-0.6.0.dist-info/top_level.txt
tsml_eval-0.6.0.dist-info/RECORD
