Metadata-Version: 2.4
Name: tsml-eval
Version: 0.6.0
Summary: A package for benchmarking time series machine learning tools.
Author-email: Matthew Middlehurst <m.b.middlehurst@soton.ac.uk>, Tony Bagnall <a.j.bagnall@soton.ac.uk>
Maintainer-email: Matthew Middlehurst <m.b.middlehurst@soton.ac.uk>, Tony Bagnall <a.j.bagnall@soton.ac.uk>
License: BSD 3-Clause License
Project-URL: homepage, https://www.timeseriesclassification.com/
Project-URL: repository, https://github.com/time-series-machine-learning/tsml-eval/
Keywords: data-science,machine-learning,time-series,time-series-classification,time-series-regression,time-series-clustering,evaluation,benchmarking
Classifier: Intended Audience :: Science/Research
Classifier: License :: OSI Approved :: BSD License
Classifier: Topic :: Scientific/Engineering
Classifier: Operating System :: Microsoft :: Windows
Classifier: Operating System :: POSIX
Classifier: Operating System :: Unix
Classifier: Operating System :: MacOS
Classifier: Programming Language :: Python
Classifier: Programming Language :: Python :: 3.9
Classifier: Programming Language :: Python :: 3.10
Classifier: Programming Language :: Python :: 3.11
Classifier: Programming Language :: Python :: 3.12
Classifier: Programming Language :: Python :: 3.13
Requires-Python: <3.14,>=3.9
License-File: LICENSE
Requires-Dist: aeon<1.2.0,>=1.0.0
Requires-Dist: tsml<0.8.0,>=0.6.0
Requires-Dist: scikit-learn<1.7.0,>=1.0.0
Requires-Dist: matplotlib
Requires-Dist: seaborn
Requires-Dist: gpustat
Requires-Dist: psutil
Provides-Extra: all-extras
Requires-Dist: aeon[all_extras]; extra == "all-extras"
Requires-Dist: tsml[all_extras]; extra == "all-extras"
Requires-Dist: xgboost; extra == "all-extras"
Provides-Extra: unstable-extras
Requires-Dist: aeon[unstable_extras]; extra == "unstable-extras"
Requires-Dist: tsml[unstable_extras]; extra == "unstable-extras"
Provides-Extra: deep-learning
Requires-Dist: aeon[dl]; extra == "deep-learning"
Provides-Extra: dev
Requires-Dist: pre-commit; extra == "dev"
Requires-Dist: pytest; extra == "dev"
Requires-Dist: pytest-randomly; extra == "dev"
Requires-Dist: pytest-timeout; extra == "dev"
Requires-Dist: pytest-xdist[psutil]; extra == "dev"
Requires-Dist: pytest-cov; extra == "dev"
Requires-Dist: pytest-rerunfailures; extra == "dev"
Provides-Extra: binder
Requires-Dist: notebook; extra == "binder"
Requires-Dist: jupyterlab; extra == "binder"
Provides-Extra: docs
Requires-Dist: sphinx<8.3.0; extra == "docs"
Requires-Dist: sphinx-design; extra == "docs"
Requires-Dist: sphinx-version-warning; extra == "docs"
Requires-Dist: sphinx_issues; extra == "docs"
Requires-Dist: sphinx-copybutton; extra == "docs"
Requires-Dist: sphinx-remove-toctrees; extra == "docs"
Requires-Dist: sphinxext-opengraph; extra == "docs"
Requires-Dist: nbsphinx; extra == "docs"
Requires-Dist: numpydoc; extra == "docs"
Requires-Dist: myst-parser; extra == "docs"
Requires-Dist: jupyter; extra == "docs"
Requires-Dist: furo; extra == "docs"
Dynamic: license-file
